README.md
setup.py
bin/pyfromroot
pyfromroot/__init__.py
pyfromroot/pr_draw.py
pyfromroot/pr_fit.py
pyfromroot/pr_load.py
pyfromroot/pr_model_decay.py
pyfromroot/pr_model_gpol1.py
pyfromroot/pr_model_logxy.py
pyfromroot/pr_model_pocall.py
pyfromroot/pr_model_polall.py
pyfromroot/pr_zoom.py
pyfromroot/prj_utils.py
pyfromroot/prun.py
pyfromroot/unitname.py
pyfromroot/version.py
pyfromroot.egg-info/PKG-INFO
pyfromroot.egg-info/SOURCES.txt
pyfromroot.egg-info/dependency_links.txt
pyfromroot.egg-info/requires.txt
pyfromroot.egg-info/top_level.txt