Metadata-Version: 2.1
Name: pyfromroot
Version: 0.2.4
Summary: Python should be callable from root environment
Home-page: https://gitlab.com/jaromrax/pyfromroot
Author: jaromrax
Author-email: jaromrax@gmail.com
License: GPL2
